mychef/__about__.py
mychef/__init__.py
mychef/app.py
mychef/cli.py
mychef/dependencies.py
mychef/access/__init__.py
mychef/access/api.py
mychef/access/cli.py
mychef/access/repository.py
mychef/access/schemas.py
mychef/access/services.py
mychef/access/tables.py
mychef/core/__init__.py
mychef/core/config.py
mychef/core/exceptions.py
mychef/core/hashing.py
mychef/core/http_exceptions.py
mychef/core/oauth.py
mychef/core/schemas.py
mychef/core/sessions.py
mychef/core/tables.py
mychef/migrations/__init__.py
mychef/migrations/alembic.ini
mychef/migrations/env.py
mychef/migrations/script.py.mako
mychef/migrations/upgrade.py
mychef/migrations/versions/37649511d28e_.py
mychef/recipes/__init__.py
mychef/recipes/api.py
mychef/recipes/repository.py
mychef/recipes/schemas.py
mychef/recipes/services.py
mychef/recipes/tables.py
mychef-0.1.1.dist-info/METADATA
mychef-0.1.1.dist-info/WHEEL
mychef-0.1.1.dist-info/entry_points.txt
mychef-0.1.1.dist-info/licenses/LICENSE
mychef-0.1.1.dist-info/RECORD
