Metadata-Version: 2.3
Name: mychef
Version: 0.1.1
Summary: A libre recipe recommendation app.
Project-URL: Homepage, https://sr.ht/~loges/mychef
Project-URL: Source, https://git.sr.ht/~loges/mychef
Project-URL: Issues, https://todo.sr.ht/~loges/mychef
Author-email: Logan Connolly <me@loganconnolly.com>
License-Expression: AGPL-3.0-or-later
License-File: LICENSE
Classifier: Development Status :: 4 - Beta
Classifier: Programming Language :: Python
Classifier: Programming Language :: Python :: 3.9
Classifier: Programming Language :: Python :: 3.10
Classifier: Programming Language :: Python :: 3.11
Classifier: Programming Language :: Python :: 3.12
Requires-Python: >=3.9
Requires-Dist: aiosqlite
Requires-Dist: alembic
Requires-Dist: click
Requires-Dist: fastapi
Requires-Dist: passlib[argon2]
Requires-Dist: pydantic-settings
Requires-Dist: python-jose
Requires-Dist: python-multipart
Requires-Dist: sqlalchemy[asyncio,mypy]
Requires-Dist: uvicorn[standard]
